sbpy/__init__.py
sbpy/_astropy_init.py
sbpy/conftest.py
sbpy/cython_version.py
sbpy/exceptions.py
sbpy/version.py
sbpy/activity/__init__.py
sbpy/activity/core.py
sbpy/activity/dust.py
sbpy/activity/gas/__init__.py
sbpy/activity/gas/core.py
sbpy/activity/gas/productionrate.py
sbpy/activity/gas/setup_package.py
sbpy/activity/gas/data/__init__.py
sbpy/activity/gas/data/schleicher88.txt
sbpy/activity/gas/tests/__init__.py
sbpy/activity/gas/tests/setup_package.py
sbpy/activity/gas/tests/test_core.py
sbpy/activity/gas/tests/test_data.py
sbpy/activity/gas/tests/test_prodrate.py
sbpy/activity/gas/tests/test_prodrate_remote.py
sbpy/activity/gas/tests/data/CH3OH.csv
sbpy/activity/gas/tests/data/CO.csv
sbpy/activity/gas/tests/data/HCN.csv
sbpy/activity/tests/__init__.py
sbpy/activity/tests/test_core.py
sbpy/activity/tests/test_dust.py
sbpy/bib/__init__.py
sbpy/bib/core.py
sbpy/bib/tests/__init__.py
sbpy/bib/tests/test_bib.py
sbpy/bib/tests/data/neatm.bib
sbpy/calib/__init__.py
sbpy/calib/core.py
sbpy/calib/setup_package.py
sbpy/calib/solar_sources.py
sbpy/calib/vega_sources.py
sbpy/calib/data/alpha_lyr_stis_008-edit.fits
sbpy/calib/data/e490-00a_2014_hires.csv
sbpy/calib/data/e490-00a_2014_lores.csv
sbpy/calib/data/solar-photometry-willmer2018.json
sbpy/calib/data/vega-photometry-willmer2018.json
sbpy/calib/tests/__init__.py
sbpy/calib/tests/test_core.py
sbpy/calib/tests/test_sun.py
sbpy/calib/tests/test_vega.py
sbpy/data/__init__.py
sbpy/data/core.py
sbpy/data/decorators.py
sbpy/data/ephem.py
sbpy/data/names.py
sbpy/data/obs.py
sbpy/data/orbit.py
sbpy/data/phys.py
sbpy/data/tests/__init__.py
sbpy/data/tests/setup_package.py
sbpy/data/tests/test_dataclass.py
sbpy/data/tests/test_decorators.py
sbpy/data/tests/test_ephem.py
sbpy/data/tests/test_ephem_remote.py
sbpy/data/tests/test_names.py
sbpy/data/tests/test_obs_remote.py
sbpy/data/tests/test_orbit_remote.py
sbpy/data/tests/test_phys_remote.py
sbpy/data/tests/data/test.txt
sbpy/extern/__init__.py
sbpy-0.2.2.dist-info/LICENSE.rst
sbpy-0.2.2.dist-info/METADATA
sbpy-0.2.2.dist-info/WHEEL
sbpy-0.2.2.dist-info/entry_points.txt
sbpy-0.2.2.dist-info/top_level.txt
sbpy-0.2.2.dist-info/RECORD
