Metadata-Version: 2.1
Name: sbpy
Version: 0.2.2
Summary: A Python Module for Small-Body Planetary Astronomy
Home-page: https://sbpy.org
Author: sbpy team
Author-email: msk@astro.umd.edu
License: BSD 3-Clause
Platform: UNKNOWN
Requires-Python: >=3.6
Requires-Dist: numpy (>=1.13.0)
Requires-Dist: astropy (<4.0,>=3.0)
Requires-Dist: astropy-helpers
Requires-Dist: matplotlib
Requires-Dist: ads
Requires-Dist: synphot (<0.2)
Requires-Dist: astroquery (>=0.4.1.dev0)
Provides-Extra: all
Requires-Dist: scipy ; extra == 'all'
Requires-Dist: ginga ; extra == 'all'
Requires-Dist: photutils ; extra == 'all'
